neojelll_api/__init__.py
neojelll_api/api.py
neojelll_api/cache.py
neojelll_api/db.py
neojelll_api/main.py
neojelll_api/message_broker.py
neojelll_api-0.1.0.dist-info/METADATA
neojelll_api-0.1.0.dist-info/WHEEL
neojelll_api-0.1.0.dist-info/RECORD
